models/message_data.py
models/response.py
models/response_model.py
models/transcript_request_model.py
routes/main.py
routes/transcription.py
service/delete_audio_file_service.py
service/transcription_service.py
service/upload_file_service.py
validation/file_audio_validation.py
whisper_transcriber/__init__.py
whisper_transcriber/client.py
whisper_transcriber/models/__init__.py
whisper_transcriber/service/__init__.py
whisper_transcriber_free-0.1.2.dist-info/licenses/LICENSE
whisper_transcriber_free-0.1.2.dist-info/METADATA
whisper_transcriber_free-0.1.2.dist-info/WHEEL
whisper_transcriber_free-0.1.2.dist-info/entry_points.txt
whisper_transcriber_free-0.1.2.dist-info/top_level.txt
whisper_transcriber_free-0.1.2.dist-info/RECORD
