Metadata-Version: 2.4
Name: whisper-transcriber-free
Version: 0.1.2
Summary: A Python SDK for audio transcription using Whisper
Home-page: https://github.com/raedrdhaounia/whisper-transcriber
Author: raedrdhaounia
Author-email: raedrdhaounia <raedrdhaounia@gmail.com>
License: MIT License
Project-URL: Homepage, https://github.com/raedrdhaounia/whisper-transcriber
Project-URL: Bug Tracker, https://github.com/raedrdhaounia/whisper-transcriber/issues
Keywords: whisper,transcription,audio,speech-to-text
Classifier: Development Status :: 3 - Alpha
Classifier: Intended Audience :: Developers
Classifier: License :: OSI Approved :: MIT License
Classifier: Programming Language :: Python :: 3
Classifier: Programming Language :: Python :: 3.8
Classifier: Programming Language :: Python :: 3.9
Classifier: Programming Language :: Python :: 3.10
Classifier: Programming Language :: Python :: 3.11
Requires-Python: >=3.8
License-File: LICENSE
Dynamic: author
Dynamic: home-page
Dynamic: license-file
Dynamic: requires-python
